{
  "strategy": "disposition",
  "started": "2026-05-24T16:20:28.596974+00:00",
  "initial_bankroll": 75.0,
  "bankroll": 73.04,
  "trades": [
    {
      "logged_at": "2026-05-24T16:20:28.597136+00:00",
      "strategy": "disposition",
      "kalshi_ticker": "KXTOPBBSPOTSDRA-26MAY30-9",
      "kalshi_title": "How many spots on the Billboard Hot 100's top 10 will Drake hold for the week of May 30, 2026?",
      "type": "favorite_buy",
      "side": "yes",
      "contracts": 2,
      "entry_price": 0.98,
      "cost": 1.96,
      "yes_mid_at_entry": 0.975,
      "true_prob_estimate": 0.99,
      "edge_at_entry": 0.02,
      "kelly_fraction": 0.03,
      "hours_left_at_entry": 131.7,
      "status": "open",
      "resolved_yes": null,
      "pnl": null,
      "settled_at": null,
      "exit_reason": null,
      "hold_to_settlement": true
    }
  ]
}