{
  "generated_at": "2026-06-07T05:49:06.678768+00:00",
  "n_scanned": 10,
  "n_signals": 3,
  "signals": [
    {
      "ticker": "KXFINALSATTEND-26JUN09-DJT",
      "title": "Will Donald J Trump attend Pro Basketball Finals Game 3: New York vs. San Antonio in 2026?",
      "type": "favorite_buy",
      "side": "yes",
      "fill_price": 0.93,
      "yes_mid": 0.92,
      "true_prob": 0.94,
      "edge": 0.02,
      "hours_left": 56.2,
      "close_time": "2026-06-09T14:00:00Z"
    },
    {
      "ticker": "KXFINALSATTEND-26JUN09-ZOH",
      "title": "Will Zohran Mamdani attend Pro Basketball Finals Game 3: New York vs. San Antonio in 2026?",
      "type": "favorite_buy",
      "side": "yes",
      "fill_price": 0.97,
      "yes_mid": 0.965,
      "true_prob": 0.985,
      "edge": 0.02,
      "hours_left": 56.2,
      "close_time": "2026-06-09T14:00:00Z"
    },
    {
      "ticker": "KXTESTMATCH-26JUN040600NZENG-ENG",
      "title": "England vs New Zealand Winner?",
      "type": "favorite_buy",
      "side": "yes",
      "fill_price": 0.95,
      "yes_mid": 0.94,
      "true_prob": 0.96,
      "edge": 0.02,
      "hours_left": 100.2,
      "close_time": "2026-06-11T10:00:00Z"
    }
  ]
}